odoo9_addon_cms_delete_content-9.0.1.0.0-py2.7-nspkg.pth
odoo9_addon_cms_delete_content-9.0.1.0.0.dist-info/top_level.txt
odoo9_addon_cms_delete_content-9.0.1.0.0.dist-info/WHEEL
odoo9_addon_cms_delete_content-9.0.1.0.0.dist-info/RECORD
odoo9_addon_cms_delete_content-9.0.1.0.0.dist-info/metadata.json
odoo9_addon_cms_delete_content-9.0.1.0.0.dist-info/DESCRIPTION.rst
odoo9_addon_cms_delete_content-9.0.1.0.0.dist-info/METADATA
odoo9_addon_cms_delete_content-9.0.1.0.0.dist-info/namespace_packages.txt
odoo_addons/cms_delete_content/__openerp__.py
odoo_addons/cms_delete_content/__init__.py
odoo_addons/cms_delete_content/README.rst
odoo_addons/cms_delete_content/models/__init__.py
odoo_addons/cms_delete_content/models/website_published.py
odoo_addons/cms_delete_content/models/test_models.py
odoo_addons/cms_delete_content/templates/assets.xml
odoo_addons/cms_delete_content/templates/delete_confirm.xml
odoo_addons/cms_delete_content/i18n/de.po
odoo_addons/cms_delete_content/controllers/main.py
odoo_addons/cms_delete_content/controllers/__init__.py
odoo_addons/cms_delete_content/tests/test_delete.py
odoo_addons/cms_delete_content/tests/__init__.py
odoo_addons/cms_delete_content/static/description/icon.png
odoo_addons/cms_delete_content/static/src/js/delete_content.js
